{"CombinedStats":{"AccomplishmentsByDate":[{"Date":"\/Date(1215666000000)\/","Count":4,"TotalCount":4},{"Date":"\/Date(1216357200000)\/","Count":2,"TotalCount":6},{"Date":"\/Date(1216530000000)\/","Count":2,"TotalCount":8},{"Date":"\/Date(1217134800000)\/","Count":1,"TotalCount":9},{"Date":"\/Date(1217566800000)\/","Count":1,"TotalCount":10},{"Date":"\/Date(1217653200000)\/","Count":1,"TotalCount":11},{"Date":"\/Date(1217912400000)\/","Count":2,"TotalCount":13},{"Date":"\/Date(1217998800000)\/","Count":11,"TotalCount":24},{"Date":"\/Date(1218085200000)\/","Count":2,"TotalCount":26},{"Date":"\/Date(1218258000000)\/","Count":16,"TotalCount":42},{"Date":"\/Date(1218344400000)\/","Count":9,"TotalCount":51},{"Date":"\/Date(1219899600000)\/","Count":3,"TotalCount":54},{"Date":"\/Date(1224738000000)\/","Count":4,"TotalCount":58},{"Date":"\/Date(1224910800000)\/","Count":10,"TotalCount":68},{"Date":"\/Date(1224997200000)\/","Count":7,"TotalCount":75},{"Date":"\/Date(1225256400000)\/","Count":10,"TotalCount":85},{"Date":"\/Date(1225429200000)\/","Count":1,"TotalCount":86},{"Date":"\/Date(1225515600000)\/","Count":20,"TotalCount":106},{"Date":"\/Date(1225602000000)\/","Count":4,"TotalCount":110},{"Date":"\/Date(1225778400000)\/","Count":1,"TotalCount":111},{"Date":"\/Date(1226124000000)\/","Count":5,"TotalCount":116},{"Date":"\/Date(1228197600000)\/","Count":4,"TotalCount":120},{"Date":"\/Date(1228284000000)\/","Count":4,"TotalCount":124},{"Date":"\/Date(1228370400000)\/","Count":7,"TotalCount":131},{"Date":"\/Date(1228456800000)\/","Count":5,"TotalCount":136},{"Date":"\/Date(1228543200000)\/","Count":10,"TotalCount":146},{"Date":"\/Date(1228629600000)\/","Count":13,"TotalCount":159},{"Date":"\/Date(1228716000000)\/","Count":8,"TotalCount":167},{"Date":"\/Date(1228802400000)\/","Count":19,"TotalCount":186},{"Date":"\/Date(1229061600000)\/","Count":12,"TotalCount":198},{"Date":"\/Date(1229148000000)\/","Count":13,"TotalCount":211},{"Date":"\/Date(1229234400000)\/","Count":3,"TotalCount":214},{"Date":"\/Date(1229666400000)\/","Count":12,"TotalCount":226},{"Date":"\/Date(1229839200000)\/","Count":16,"TotalCount":242},{"Date":"\/Date(1229925600000)\/","Count":3,"TotalCount":245},{"Date":"\/Date(1230098400000)\/","Count":4,"TotalCount":249},{"Date":"\/Date(1230271200000)\/","Count":1,"TotalCount":250},{"Date":"\/Date(1230357600000)\/","Count":2,"TotalCount":252},{"Date":"\/Date(1230444000000)\/","Count":20,"TotalCount":272},{"Date":"\/Date(1230616800000)\/","Count":4,"TotalCount":276},{"Date":"\/Date(1230703200000)\/","Count":3,"TotalCount":279},{"Date":"\/Date(1230962400000)\/","Count":4,"TotalCount":283},{"Date":"\/Date(1231048800000)\/","Count":9,"TotalCount":292},{"Date":"\/Date(1231135200000)\/","Count":2,"TotalCount":294},{"Date":"\/Date(1231567200000)\/","Count":3,"TotalCount":297},{"Date":"\/Date(1231653600000)\/","Count":5,"TotalCount":302},{"Date":"\/Date(1231912800000)\/","Count":2,"TotalCount":304},{"Date":"\/Date(1231999200000)\/","Count":3,"TotalCount":307},{"Date":"\/Date(1232085600000)\/","Count":2,"TotalCount":309},{"Date":"\/Date(1232172000000)\/","Count":6,"TotalCount":315},{"Date":"\/Date(1232258400000)\/","Count":2,"TotalCount":317},{"Date":"\/Date(1232344800000)\/","Count":5,"TotalCount":322},{"Date":"\/Date(1232517600000)\/","Count":1,"TotalCount":323},{"Date":"\/Date(1232690400000)\/","Count":2,"TotalCount":325},{"Date":"\/Date(1232776800000)\/","Count":2,"TotalCount":327},{"Date":"\/Date(1232863200000)\/","Count":2,"TotalCount":329},{"Date":"\/Date(1233208800000)\/","Count":1,"TotalCount":330},{"Date":"\/Date(1233554400000)\/","Count":2,"TotalCount":332},{"Date":"\/Date(1234072800000)\/","Count":1,"TotalCount":333},{"Date":"\/Date(1234159200000)\/","Count":4,"TotalCount":337},{"Date":"\/Date(1234245600000)\/","Count":1,"TotalCount":338},{"Date":"\/Date(1234332000000)\/","Count":3,"TotalCount":341},{"Date":"\/Date(1234418400000)\/","Count":7,"TotalCount":348},{"Date":"\/Date(1234504800000)\/","Count":6,"TotalCount":354},{"Date":"\/Date(1234591200000)\/","Count":3,"TotalCount":357},{"Date":"\/Date(1234677600000)\/","Count":7,"TotalCount":364},{"Date":"\/Date(1234850400000)\/","Count":1,"TotalCount":365},{"Date":"\/Date(1235109600000)\/","Count":4,"TotalCount":369},{"Date":"\/Date(1235196000000)\/","Count":9,"TotalCount":378},{"Date":"\/Date(1235282400000)\/","Count":3,"TotalCount":381},{"Date":"\/Date(1235368800000)\/","Count":1,"TotalCount":382},{"Date":"\/Date(1235628000000)\/","Count":2,"TotalCount":384},{"Date":"\/Date(1235714400000)\/","Count":3,"TotalCount":387},{"Date":"\/Date(1235800800000)\/","Count":3,"TotalCount":390},{"Date":"\/Date(1235887200000)\/","Count":2,"TotalCount":392},{"Date":"\/Date(1236060000000)\/","Count":3,"TotalCount":395},{"Date":"\/Date(1236319200000)\/","Count":7,"TotalCount":402},{"Date":"\/Date(1236405600000)\/","Count":9,"TotalCount":411},{"Date":"\/Date(1236492000000)\/","Count":5,"TotalCount":416},{"Date":"\/Date(1236574800000)\/","Count":10,"TotalCount":426},{"Date":"\/Date(1236661200000)\/","Count":1,"TotalCount":427},{"Date":"\/Date(1236834000000)\/","Count":3,"TotalCount":430},{"Date":"\/Date(1236920400000)\/","Count":2,"TotalCount":432},{"Date":"\/Date(1237093200000)\/","Count":2,"TotalCount":434},{"Date":"\/Date(1237525200000)\/","Count":1,"TotalCount":435},{"Date":"\/Date(1237611600000)\/","Count":3,"TotalCount":438},{"Date":"\/Date(1237698000000)\/","Count":3,"TotalCount":441},{"Date":"\/Date(1238216400000)\/","Count":5,"TotalCount":446},{"Date":"\/Date(1238302800000)\/","Count":9,"TotalCount":455},{"Date":"\/Date(1238389200000)\/","Count":6,"TotalCount":461},{"Date":"\/Date(1238907600000)\/","Count":9,"TotalCount":470},{"Date":"\/Date(1239166800000)\/","Count":3,"TotalCount":473},{"Date":"\/Date(1239426000000)\/","Count":3,"TotalCount":476},{"Date":"\/Date(1239512400000)\/","Count":2,"TotalCount":478},{"Date":"\/Date(1239598800000)\/","Count":1,"TotalCount":479},{"Date":"\/Date(1239771600000)\/","Count":1,"TotalCount":480},{"Date":"\/Date(1239944400000)\/","Count":2,"TotalCount":482},{"Date":"\/Date(1240030800000)\/","Count":7,"TotalCount":489},{"Date":"\/Date(1240117200000)\/","Count":5,"TotalCount":494},{"Date":"\/Date(1240376400000)\/","Count":1,"TotalCount":495},{"Date":"\/Date(1240462800000)\/","Count":1,"TotalCount":496},{"Date":"\/Date(1240549200000)\/","Count":7,"TotalCount":503},{"Date":"\/Date(1240635600000)\/","Count":3,"TotalCount":506},{"Date":"\/Date(1240722000000)\/","Count":3,"TotalCount":509},{"Date":"\/Date(1240894800000)\/","Count":2,"TotalCount":511},{"Date":"\/Date(1240981200000)\/","Count":2,"TotalCount":513},{"Date":"\/Date(1241154000000)\/","Count":6,"TotalCount":519},{"Date":"\/Date(1241240400000)\/","Count":3,"TotalCount":522},{"Date":"\/Date(1241326800000)\/","Count":8,"TotalCount":530},{"Date":"\/Date(1241672400000)\/","Count":16,"TotalCount":546},{"Date":"\/Date(1241758800000)\/","Count":4,"TotalCount":550},{"Date":"\/Date(1241845200000)\/","Count":5,"TotalCount":555},{"Date":"\/Date(1241931600000)\/","Count":11,"TotalCount":566},{"Date":"\/Date(1242018000000)\/","Count":3,"TotalCount":569},{"Date":"\/Date(1242190800000)\/","Count":1,"TotalCount":570},{"Date":"\/Date(1242277200000)\/","Count":1,"TotalCount":571},{"Date":"\/Date(1242363600000)\/","Count":3,"TotalCount":574},{"Date":"\/Date(1242536400000)\/","Count":2,"TotalCount":576},{"Date":"\/Date(1242622800000)\/","Count":2,"TotalCount":578},{"Date":"\/Date(1242709200000)\/","Count":1,"TotalCount":579},{"Date":"\/Date(1242795600000)\/","Count":2,"TotalCount":581},{"Date":"\/Date(1242968400000)\/","Count":1,"TotalCount":582},{"Date":"\/Date(1243054800000)\/","Count":7,"TotalCount":589},{"Date":"\/Date(1243141200000)\/","Count":2,"TotalCount":591},{"Date":"\/Date(1243659600000)\/","Count":9,"TotalCount":600},{"Date":"\/Date(1243746000000)\/","Count":9,"TotalCount":609},{"Date":"\/Date(1244005200000)\/","Count":3,"TotalCount":612},{"Date":"\/Date(1244091600000)\/","Count":4,"TotalCount":616},{"Date":"\/Date(1244178000000)\/","Count":3,"TotalCount":619},{"Date":"\/Date(1244264400000)\/","Count":5,"TotalCount":624},{"Date":"\/Date(1244869200000)\/","Count":3,"TotalCount":627},{"Date":"\/Date(1244955600000)\/","Count":2,"TotalCount":629},{"Date":"\/Date(1245301200000)\/","Count":1,"TotalCount":630},{"Date":"\/Date(1245387600000)\/","Count":1,"TotalCount":631},{"Date":"\/Date(1245560400000)\/","Count":8,"TotalCount":639},{"Date":"\/Date(1245646800000)\/","Count":2,"TotalCount":641},{"Date":"\/Date(1245992400000)\/","Count":8,"TotalCount":649},{"Date":"\/Date(1246165200000)\/","Count":2,"TotalCount":651},{"Date":"\/Date(1246510800000)\/","Count":12,"TotalCount":663},{"Date":"\/Date(1246770000000)\/","Count":4,"TotalCount":667},{"Date":"\/Date(1247029200000)\/","Count":1,"TotalCount":668},{"Date":"\/Date(1247202000000)\/","Count":1,"TotalCount":669},{"Date":"\/Date(1247288400000)\/","Count":1,"TotalCount":670},{"Date":"\/Date(1248584400000)\/","Count":3,"TotalCount":673},{"Date":"\/Date(1248757200000)\/","Count":2,"TotalCount":675},{"Date":"\/Date(1249016400000)\/","Count":1,"TotalCount":676},{"Date":"\/Date(1249362000000)\/","Count":5,"TotalCount":681},{"Date":"\/Date(1249707600000)\/","Count":4,"TotalCount":685},{"Date":"\/Date(1249794000000)\/","Count":4,"TotalCount":689},{"Date":"\/Date(1250226000000)\/","Count":1,"TotalCount":690},{"Date":"\/Date(1250312400000)\/","Count":1,"TotalCount":691},{"Date":"\/Date(1250485200000)\/","Count":5,"TotalCount":696},{"Date":"\/Date(1250571600000)\/","Count":5,"TotalCount":701},{"Date":"\/Date(1250744400000)\/","Count":4,"TotalCount":705},{"Date":"\/Date(1250830800000)\/","Count":4,"TotalCount":709},{"Date":"\/Date(1250917200000)\/","Count":8,"TotalCount":717},{"Date":"\/Date(1251003600000)\/","Count":6,"TotalCount":723},{"Date":"\/Date(1251435600000)\/","Count":5,"TotalCount":728},{"Date":"\/Date(1251954000000)\/","Count":10,"TotalCount":738},{"Date":"\/Date(1252040400000)\/","Count":21,"TotalCount":759},{"Date":"\/Date(1252126800000)\/","Count":1,"TotalCount":760},{"Date":"\/Date(1252213200000)\/","Count":4,"TotalCount":764},{"Date":"\/Date(1252299600000)\/","Count":6,"TotalCount":770},{"Date":"\/Date(1252731600000)\/","Count":4,"TotalCount":774},{"Date":"\/Date(1252818000000)\/","Count":1,"TotalCount":775},{"Date":"\/Date(1252904400000)\/","Count":10,"TotalCount":785},{"Date":"\/Date(1253077200000)\/","Count":10,"TotalCount":795},{"Date":"\/Date(1253163600000)\/","Count":3,"TotalCount":798},{"Date":"\/Date(1253250000000)\/","Count":10,"TotalCount":808},{"Date":"\/Date(1253422800000)\/","Count":1,"TotalCount":809},{"Date":"\/Date(1253941200000)\/","Count":4,"TotalCount":813},{"Date":"\/Date(1254027600000)\/","Count":4,"TotalCount":817},{"Date":"\/Date(1254114000000)\/","Count":1,"TotalCount":818},{"Date":"\/Date(1254200400000)\/","Count":1,"TotalCount":819},{"Date":"\/Date(1254459600000)\/","Count":2,"TotalCount":821},{"Date":"\/Date(1254546000000)\/","Count":2,"TotalCount":823},{"Date":"\/Date(1255755600000)\/","Count":2,"TotalCount":825},{"Date":"\/Date(1255842000000)\/","Count":3,"TotalCount":828},{"Date":"\/Date(1256101200000)\/","Count":1,"TotalCount":829},{"Date":"\/Date(1256187600000)\/","Count":13,"TotalCount":842},{"Date":"\/Date(1256274000000)\/","Count":6,"TotalCount":848},{"Date":"\/Date(1256446800000)\/","Count":10,"TotalCount":858},{"Date":"\/Date(1256878800000)\/","Count":2,"TotalCount":860},{"Date":"\/Date(1258178400000)\/","Count":2,"TotalCount":862},{"Date":"\/Date(1258264800000)\/","Count":6,"TotalCount":868},{"Date":"\/Date(1258351200000)\/","Count":2,"TotalCount":870},{"Date":"\/Date(1258437600000)\/","Count":1,"TotalCount":871},{"Date":"\/Date(1258524000000)\/","Count":1,"TotalCount":872},{"Date":"\/Date(1259992800000)\/","Count":12,"TotalCount":884},{"Date":"\/Date(1260079200000)\/","Count":5,"TotalCount":889},{"Date":"\/Date(1260511200000)\/","Count":14,"TotalCount":903},{"Date":"\/Date(1260597600000)\/","Count":3,"TotalCount":906},{"Date":"\/Date(1260684000000)\/","Count":5,"TotalCount":911},{"Date":"\/Date(1261116000000)\/","Count":23,"TotalCount":934},{"Date":"\/Date(1261202400000)\/","Count":4,"TotalCount":938},{"Date":"\/Date(1261634400000)\/","Count":2,"TotalCount":940},{"Date":"\/Date(1262930400000)\/","Count":1,"TotalCount":941},{"Date":"\/Date(1263016800000)\/","Count":9,"TotalCount":950},{"Date":"\/Date(1263103200000)\/","Count":8,"TotalCount":958},{"Date":"\/Date(1263189600000)\/","Count":1,"TotalCount":959},{"Date":"\/Date(1263276000000)\/","Count":1,"TotalCount":960},{"Date":"\/Date(1263448800000)\/","Count":2,"TotalCount":962},{"Date":"\/Date(1263535200000)\/","Count":2,"TotalCount":964},{"Date":"\/Date(1263621600000)\/","Count":5,"TotalCount":969},{"Date":"\/Date(1263708000000)\/","Count":7,"TotalCount":976},{"Date":"\/Date(1263794400000)\/","Count":2,"TotalCount":978},{"Date":"\/Date(1264140000000)\/","Count":11,"TotalCount":989},{"Date":"\/Date(1264226400000)\/","Count":6,"TotalCount":995},{"Date":"\/Date(1264312800000)\/","Count":5,"TotalCount":1000},{"Date":"\/Date(1264485600000)\/","Count":4,"TotalCount":1004},{"Date":"\/Date(1264744800000)\/","Count":8,"TotalCount":1012},{"Date":"\/Date(1264917600000)\/","Count":5,"TotalCount":1017},{"Date":"\/Date(1265004000000)\/","Count":2,"TotalCount":1019},{"Date":"\/Date(1265090400000)\/","Count":7,"TotalCount":1026},{"Date":"\/Date(1266472800000)\/","Count":1,"TotalCount":1027},{"Date":"\/Date(1266559200000)\/","Count":1,"TotalCount":1028},{"Date":"\/Date(1266732000000)\/","Count":2,"TotalCount":1030},{"Date":"\/Date(1267077600000)\/","Count":4,"TotalCount":1034},{"Date":"\/Date(1267164000000)\/","Count":1,"TotalCount":1035},{"Date":"\/Date(1267250400000)\/","Count":2,"TotalCount":1037},{"Date":"\/Date(1267336800000)\/","Count":2,"TotalCount":1039},{"Date":"\/Date(1267768800000)\/","Count":3,"TotalCount":1042},{"Date":"\/Date(1267855200000)\/","Count":7,"TotalCount":1049},{"Date":"\/Date(1267941600000)\/","Count":8,"TotalCount":1057},{"Date":"\/Date(1268974800000)\/","Count":5,"TotalCount":1062},{"Date":"\/Date(1269061200000)\/","Count":2,"TotalCount":1064},{"Date":"\/Date(1269147600000)\/","Count":4,"TotalCount":1068},{"Date":"\/Date(1269493200000)\/","Count":1,"TotalCount":1069},{"Date":"\/Date(1269666000000)\/","Count":1,"TotalCount":1070},{"Date":"\/Date(1269752400000)\/","Count":3,"TotalCount":1073},{"Date":"\/Date(1269838800000)\/","Count":1,"TotalCount":1074},{"Date":"\/Date(1269925200000)\/","Count":3,"TotalCount":1077},{"Date":"\/Date(1270184400000)\/","Count":1,"TotalCount":1078},{"Date":"\/Date(1270270800000)\/","Count":2,"TotalCount":1080},{"Date":"\/Date(1270357200000)\/","Count":2,"TotalCount":1082},{"Date":"\/Date(1270702800000)\/","Count":16,"TotalCount":1098},{"Date":"\/Date(1270789200000)\/","Count":3,"TotalCount":1101},{"Date":"\/Date(1270875600000)\/","Count":23,"TotalCount":1124},{"Date":"\/Date(1271221200000)\/","Count":1,"TotalCount":1125},{"Date":"\/Date(1271394000000)\/","Count":2,"TotalCount":1127},{"Date":"\/Date(1271480400000)\/","Count":24,"TotalCount":1151},{"Date":"\/Date(1271566800000)\/","Count":8,"TotalCount":1159},{"Date":"\/Date(1271653200000)\/","Count":1,"TotalCount":1160},{"Date":"\/Date(1271739600000)\/","Count":1,"TotalCount":1161},{"Date":"\/Date(1271998800000)\/","Count":14,"TotalCount":1175},{"Date":"\/Date(1272085200000)\/","Count":3,"TotalCount":1178},{"Date":"\/Date(1272603600000)\/","Count":3,"TotalCount":1181},{"Date":"\/Date(1272690000000)\/","Count":6,"TotalCount":1187},{"Date":"\/Date(1272776400000)\/","Count":7,"TotalCount":1194},{"Date":"\/Date(1273035600000)\/","Count":2,"TotalCount":1196},{"Date":"\/Date(1273294800000)\/","Count":3,"TotalCount":1199},{"Date":"\/Date(1273381200000)\/","Count":2,"TotalCount":1201},{"Date":"\/Date(1273986000000)\/","Count":4,"TotalCount":1205},{"Date":"\/Date(1274158800000)\/","Count":3,"TotalCount":1208},{"Date":"\/Date(1274245200000)\/","Count":2,"TotalCount":1210},{"Date":"\/Date(1274331600000)\/","Count":2,"TotalCount":1212},{"Date":"\/Date(1275109200000)\/","Count":2,"TotalCount":1214},{"Date":"\/Date(1275973200000)\/","Count":1,"TotalCount":1215},{"Date":"\/Date(1276405200000)\/","Count":1,"TotalCount":1216},{"Date":"\/Date(1276664400000)\/","Count":1,"TotalCount":1217},{"Date":"\/Date(1276837200000)\/","Count":3,"TotalCount":1220},{"Date":"\/Date(1277010000000)\/","Count":1,"TotalCount":1221},{"Date":"\/Date(1277442000000)\/","Count":1,"TotalCount":1222},{"Date":"\/Date(1277528400000)\/","Count":3,"TotalCount":1225},{"Date":"\/Date(1277614800000)\/","Count":4,"TotalCount":1229},{"Date":"\/Date(1277701200000)\/","Count":1,"TotalCount":1230},{"Date":"\/Date(1277874000000)\/","Count":3,"TotalCount":1233},{"Date":"\/Date(1279342800000)\/","Count":1,"TotalCount":1234},{"Date":"\/Date(1281157200000)\/","Count":1,"TotalCount":1235},{"Date":"\/Date(1281848400000)\/","Count":2,"TotalCount":1237},{"Date":"\/Date(1282021200000)\/","Count":3,"TotalCount":1240},{"Date":"\/Date(1282280400000)\/","Count":7,"TotalCount":1247},{"Date":"\/Date(1282366800000)\/","Count":1,"TotalCount":1248},{"Date":"\/Date(1282539600000)\/","Count":1,"TotalCount":1249},{"Date":"\/Date(1282626000000)\/","Count":1,"TotalCount":1250},{"Date":"\/Date(1282885200000)\/","Count":2,"TotalCount":1252},{"Date":"\/Date(1282971600000)\/","Count":3,"TotalCount":1255},{"Date":"\/Date(1283749200000)\/","Count":1,"TotalCount":1256},{"Date":"\/Date(1284094800000)\/","Count":3,"TotalCount":1259},{"Date":"\/Date(1284181200000)\/","Count":3,"TotalCount":1262},{"Date":"\/Date(1284526800000)\/","Count":3,"TotalCount":1265},{"Date":"\/Date(1284613200000)\/","Count":1,"TotalCount":1266},{"Date":"\/Date(1284699600000)\/","Count":1,"TotalCount":1267},{"Date":"\/Date(1284786000000)\/","Count":4,"TotalCount":1271},{"Date":"\/Date(1284872400000)\/","Count":3,"TotalCount":1274},{"Date":"\/Date(1284958800000)\/","Count":1,"TotalCount":1275},{"Date":"\/Date(1285045200000)\/","Count":2,"TotalCount":1277},{"Date":"\/Date(1285304400000)\/","Count":5,"TotalCount":1282},{"Date":"\/Date(1285390800000)\/","Count":3,"TotalCount":1285},{"Date":"\/Date(1285477200000)\/","Count":3,"TotalCount":1288},{"Date":"\/Date(1285563600000)\/","Count":1,"TotalCount":1289},{"Date":"\/Date(1285736400000)\/","Count":3,"TotalCount":1292},{"Date":"\/Date(1285822800000)\/","Count":8,"TotalCount":1300},{"Date":"\/Date(1285909200000)\/","Count":1,"TotalCount":1301},{"Date":"\/Date(1286686800000)\/","Count":11,"TotalCount":1312},{"Date":"\/Date(1286773200000)\/","Count":2,"TotalCount":1314},{"Date":"\/Date(1286859600000)\/","Count":1,"TotalCount":1315},{"Date":"\/Date(1286946000000)\/","Count":1,"TotalCount":1316},{"Date":"\/Date(1287118800000)\/","Count":2,"TotalCount":1318},{"Date":"\/Date(1287205200000)\/","Count":7,"TotalCount":1325},{"Date":"\/Date(1287291600000)\/","Count":7,"TotalCount":1332},{"Date":"\/Date(1287550800000)\/","Count":1,"TotalCount":1333},{"Date":"\/Date(1287810000000)\/","Count":2,"TotalCount":1335},{"Date":"\/Date(1288069200000)\/","Count":4,"TotalCount":1339},{"Date":"\/Date(1288501200000)\/","Count":2,"TotalCount":1341},{"Date":"\/Date(1289019600000)\/","Count":2,"TotalCount":1343},{"Date":"\/Date(1289541600000)\/","Count":1,"TotalCount":1344},{"Date":"\/Date(1290837600000)\/","Count":9,"TotalCount":1353},{"Date":"\/Date(1290924000000)\/","Count":6,"TotalCount":1359},{"Date":"\/Date(1291874400000)\/","Count":6,"TotalCount":1365},{"Date":"\/Date(1292652000000)\/","Count":2,"TotalCount":1367},{"Date":"\/Date(1293861600000)\/","Count":5,"TotalCount":1372},{"Date":"\/Date(1296972000000)\/","Count":6,"TotalCount":1378},{"Date":"\/Date(1297144800000)\/","Count":3,"TotalCount":1381},{"Date":"\/Date(1297317600000)\/","Count":2,"TotalCount":1383},{"Date":"\/Date(1297404000000)\/","Count":3,"TotalCount":1386},{"Date":"\/Date(1297576800000)\/","Count":7,"TotalCount":1393},{"Date":"\/Date(1297749600000)\/","Count":6,"TotalCount":1399},{"Date":"\/Date(1298008800000)\/","Count":9,"TotalCount":1408},{"Date":"\/Date(1298095200000)\/","Count":4,"TotalCount":1412},{"Date":"\/Date(1298268000000)\/","Count":2,"TotalCount":1414},{"Date":"\/Date(1298786400000)\/","Count":6,"TotalCount":1420},{"Date":"\/Date(1299736800000)\/","Count":1,"TotalCount":1421},{"Date":"\/Date(1299823200000)\/","Count":2,"TotalCount":1423},{"Date":"\/Date(1299996000000)\/","Count":3,"TotalCount":1426},{"Date":"\/Date(1300510800000)\/","Count":9,"TotalCount":1435},{"Date":"\/Date(1300856400000)\/","Count":2,"TotalCount":1437},{"Date":"\/Date(1300942800000)\/","Count":5,"TotalCount":1442},{"Date":"\/Date(1301029200000)\/","Count":3,"TotalCount":1445},{"Date":"\/Date(1301115600000)\/","Count":8,"TotalCount":1453},{"Date":"\/Date(1301202000000)\/","Count":8,"TotalCount":1461},{"Date":"\/Date(1301288400000)\/","Count":1,"TotalCount":1462},{"Date":"\/Date(1301374800000)\/","Count":1,"TotalCount":1463},{"Date":"\/Date(1301720400000)\/","Count":8,"TotalCount":1471},{"Date":"\/Date(1301806800000)\/","Count":1,"TotalCount":1472},{"Date":"\/Date(1302238800000)\/","Count":9,"TotalCount":1481},{"Date":"\/Date(1302325200000)\/","Count":4,"TotalCount":1485},{"Date":"\/Date(1303275600000)\/","Count":1,"TotalCount":1486},{"Date":"\/Date(1303362000000)\/","Count":6,"TotalCount":1492},{"Date":"\/Date(1304139600000)\/","Count":5,"TotalCount":1497},{"Date":"\/Date(1304658000000)\/","Count":3,"TotalCount":1500},{"Date":"\/Date(1304830800000)\/","Count":5,"TotalCount":1505},{"Date":"\/Date(1305176400000)\/","Count":3,"TotalCount":1508},{"Date":"\/Date(1305262800000)\/","Count":9,"TotalCount":1517},{"Date":"\/Date(1305435600000)\/","Count":2,"TotalCount":1519},{"Date":"\/Date(1305522000000)\/","Count":6,"TotalCount":1525},{"Date":"\/Date(1305608400000)\/","Count":6,"TotalCount":1531},{"Date":"\/Date(1305694800000)\/","Count":3,"TotalCount":1534},{"Date":"\/Date(1305781200000)\/","Count":2,"TotalCount":1536},{"Date":"\/Date(1305867600000)\/","Count":1,"TotalCount":1537},{"Date":"\/Date(1305954000000)\/","Count":8,"TotalCount":1545},{"Date":"\/Date(1306472400000)\/","Count":8,"TotalCount":1553},{"Date":"\/Date(1306558800000)\/","Count":4,"TotalCount":1557},{"Date":"\/Date(1306645200000)\/","Count":15,"TotalCount":1572},{"Date":"\/Date(1306731600000)\/","Count":12,"TotalCount":1584},{"Date":"\/Date(1307077200000)\/","Count":17,"TotalCount":1601},{"Date":"\/Date(1307163600000)\/","Count":4,"TotalCount":1605},{"Date":"\/Date(1307250000000)\/","Count":22,"TotalCount":1627},{"Date":"\/Date(1307336400000)\/","Count":5,"TotalCount":1632},{"Date":"\/Date(1307422800000)\/","Count":9,"TotalCount":1641},{"Date":"\/Date(1307595600000)\/","Count":7,"TotalCount":1648},{"Date":"\/Date(1307682000000)\/","Count":9,"TotalCount":1657},{"Date":"\/Date(1307768400000)\/","Count":4,"TotalCount":1661},{"Date":"\/Date(1308027600000)\/","Count":5,"TotalCount":1666},{"Date":"\/Date(1308114000000)\/","Count":7,"TotalCount":1673},{"Date":"\/Date(1308200400000)\/","Count":4,"TotalCount":1677},{"Date":"\/Date(1308286800000)\/","Count":7,"TotalCount":1684},{"Date":"\/Date(1308459600000)\/","Count":7,"TotalCount":1691},{"Date":"\/Date(1308632400000)\/","Count":3,"TotalCount":1694},{"Date":"\/Date(1308978000000)\/","Count":2,"TotalCount":1696},{"Date":"\/Date(1309064400000)\/","Count":2,"TotalCount":1698},{"Date":"\/Date(1309150800000)\/","Count":3,"TotalCount":1701},{"Date":"\/Date(1309669200000)\/","Count":1,"TotalCount":1702},{"Date":"\/Date(1309755600000)\/","Count":3,"TotalCount":1705},{"Date":"\/Date(1310101200000)\/","Count":1,"TotalCount":1706},{"Date":"\/Date(1310274000000)\/","Count":7,"TotalCount":1713},{"Date":"\/Date(1310792400000)\/","Count":23,"TotalCount":1736},{"Date":"\/Date(1310878800000)\/","Count":5,"TotalCount":1741},{"Date":"\/Date(1310965200000)\/","Count":3,"TotalCount":1744},{"Date":"\/Date(1311224400000)\/","Count":3,"TotalCount":1747},{"Date":"\/Date(1311397200000)\/","Count":19,"TotalCount":1766},{"Date":"\/Date(1312261200000)\/","Count":3,"TotalCount":1769},{"Date":"\/Date(1312347600000)\/","Count":2,"TotalCount":1771},{"Date":"\/Date(1312434000000)\/","Count":4,"TotalCount":1775},{"Date":"\/Date(1312520400000)\/","Count":18,"TotalCount":1793},{"Date":"\/Date(1312606800000)\/","Count":12,"TotalCount":1805},{"Date":"\/Date(1312952400000)\/","Count":8,"TotalCount":1813},{"Date":"\/Date(1313038800000)\/","Count":7,"TotalCount":1820},{"Date":"\/Date(1313125200000)\/","Count":5,"TotalCount":1825},{"Date":"\/Date(1313211600000)\/","Count":4,"TotalCount":1829},{"Date":"\/Date(1313298000000)\/","Count":3,"TotalCount":1832},{"Date":"\/Date(1313384400000)\/","Count":1,"TotalCount":1833},{"Date":"\/Date(1313470800000)\/","Count":3,"TotalCount":1836},{"Date":"\/Date(1313643600000)\/","Count":3,"TotalCount":1839},{"Date":"\/Date(1313730000000)\/","Count":5,"TotalCount":1844},{"Date":"\/Date(1313816400000)\/","Count":4,"TotalCount":1848},{"Date":"\/Date(1313989200000)\/","Count":2,"TotalCount":1850},{"Date":"\/Date(1314075600000)\/","Count":2,"TotalCount":1852},{"Date":"\/Date(1314248400000)\/","Count":1,"TotalCount":1853},{"Date":"\/Date(1314421200000)\/","Count":14,"TotalCount":1867},{"Date":"\/Date(1314507600000)\/","Count":2,"TotalCount":1869},{"Date":"\/Date(1314594000000)\/","Count":1,"TotalCount":1870},{"Date":"\/Date(1314939600000)\/","Count":1,"TotalCount":1871},{"Date":"\/Date(1315198800000)\/","Count":3,"TotalCount":1874},{"Date":"\/Date(1315630800000)\/","Count":4,"TotalCount":1878},{"Date":"\/Date(1315717200000)\/","Count":11,"TotalCount":1889},{"Date":"\/Date(1315803600000)\/","Count":1,"TotalCount":1890},{"Date":"\/Date(1315976400000)\/","Count":2,"TotalCount":1892},{"Date":"\/Date(1316062800000)\/","Count":2,"TotalCount":1894},{"Date":"\/Date(1316149200000)\/","Count":5,"TotalCount":1899},{"Date":"\/Date(1316235600000)\/","Count":5,"TotalCount":1904},{"Date":"\/Date(1316322000000)\/","Count":4,"TotalCount":1908},{"Date":"\/Date(1316408400000)\/","Count":3,"TotalCount":1911},{"Date":"\/Date(1316840400000)\/","Count":36,"TotalCount":1947},{"Date":"\/Date(1316926800000)\/","Count":8,"TotalCount":1955},{"Date":"\/Date(1317099600000)\/","Count":3,"TotalCount":1958},{"Date":"\/Date(1317358800000)\/","Count":10,"TotalCount":1968},{"Date":"\/Date(1317445200000)\/","Count":13,"TotalCount":1981},{"Date":"\/Date(1317531600000)\/","Count":14,"TotalCount":1995},{"Date":"\/Date(1317877200000)\/","Count":1,"TotalCount":1996},{"Date":"\/Date(1317963600000)\/","Count":6,"TotalCount":2002},{"Date":"\/Date(1318050000000)\/","Count":12,"TotalCount":2014},{"Date":"\/Date(1318136400000)\/","Count":4,"TotalCount":2018},{"Date":"\/Date(1318222800000)\/","Count":8,"TotalCount":2026},{"Date":"\/Date(1318309200000)\/","Count":5,"TotalCount":2031},{"Date":"\/Date(1318395600000)\/","Count":9,"TotalCount":2040},{"Date":"\/Date(1318482000000)\/","Count":6,"TotalCount":2046},{"Date":"\/Date(1318568400000)\/","Count":20,"TotalCount":2066},{"Date":"\/Date(1318654800000)\/","Count":7,"TotalCount":2073},{"Date":"\/Date(1318741200000)\/","Count":11,"TotalCount":2084},{"Date":"\/Date(1318914000000)\/","Count":1,"TotalCount":2085},{"Date":"\/Date(1319173200000)\/","Count":1,"TotalCount":2086},{"Date":"\/Date(1319259600000)\/","Count":5,"TotalCount":2091},{"Date":"\/Date(1319346000000)\/","Count":5,"TotalCount":2096},{"Date":"\/Date(1319864400000)\/","Count":9,"TotalCount":2105},{"Date":"\/Date(1319950800000)\/","Count":30,"TotalCount":2135},{"Date":"\/Date(1320037200000)\/","Count":10,"TotalCount":2145},{"Date":"\/Date(1320123600000)\/","Count":5,"TotalCount":2150},{"Date":"\/Date(1320210000000)\/","Count":5,"TotalCount":2155},{"Date":"\/Date(1320296400000)\/","Count":6,"TotalCount":2161},{"Date":"\/Date(1320382800000)\/","Count":19,"TotalCount":2180},{"Date":"\/Date(1320469200000)\/","Count":16,"TotalCount":2196},{"Date":"\/Date(1320555600000)\/","Count":12,"TotalCount":2208},{"Date":"\/Date(1320645600000)\/","Count":1,"TotalCount":2209},{"Date":"\/Date(1320732000000)\/","Count":2,"TotalCount":2211},{"Date":"\/Date(1320818400000)\/","Count":2,"TotalCount":2213},{"Date":"\/Date(1320904800000)\/","Count":12,"TotalCount":2225},{"Date":"\/Date(1320991200000)\/","Count":12,"TotalCount":2237},{"Date":"\/Date(1321077600000)\/","Count":7,"TotalCount":2244},{"Date":"\/Date(1321164000000)\/","Count":3,"TotalCount":2247},{"Date":"\/Date(1321336800000)\/","Count":12,"TotalCount":2259},{"Date":"\/Date(1321423200000)\/","Count":5,"TotalCount":2264},{"Date":"\/Date(1321509600000)\/","Count":1,"TotalCount":2265},{"Date":"\/Date(1321596000000)\/","Count":8,"TotalCount":2273},{"Date":"\/Date(1321768800000)\/","Count":19,"TotalCount":2292},{"Date":"\/Date(1321855200000)\/","Count":1,"TotalCount":2293},{"Date":"\/Date(1321941600000)\/","Count":1,"TotalCount":2294},{"Date":"\/Date(1322028000000)\/","Count":3,"TotalCount":2297},{"Date":"\/Date(1322200800000)\/","Count":10,"TotalCount":2307},{"Date":"\/Date(1322287200000)\/","Count":12,"TotalCount":2319},{"Date":"\/Date(1322373600000)\/","Count":1,"TotalCount":2320},{"Date":"\/Date(1322460000000)\/","Count":11,"TotalCount":2331},{"Date":"\/Date(1322546400000)\/","Count":1,"TotalCount":2332},{"Date":"\/Date(1322632800000)\/","Count":3,"TotalCount":2335},{"Date":"\/Date(1322719200000)\/","Count":1,"TotalCount":2336},{"Date":"\/Date(1322805600000)\/","Count":3,"TotalCount":2339},{"Date":"\/Date(1322892000000)\/","Count":4,"TotalCount":2343},{"Date":"\/Date(1322978400000)\/","Count":3,"TotalCount":2346},{"Date":"\/Date(1323064800000)\/","Count":3,"TotalCount":2349},{"Date":"\/Date(1323151200000)\/","Count":2,"TotalCount":2351},{"Date":"\/Date(1323237600000)\/","Count":3,"TotalCount":2354},{"Date":"\/Date(1323324000000)\/","Count":5,"TotalCount":2359},{"Date":"\/Date(1323410400000)\/","Count":5,"TotalCount":2364},{"Date":"\/Date(1323496800000)\/","Count":14,"TotalCount":2378},{"Date":"\/Date(1323583200000)\/","Count":6,"TotalCount":2384},{"Date":"\/Date(1323669600000)\/","Count":1,"TotalCount":2385},{"Date":"\/Date(1323756000000)\/","Count":2,"TotalCount":2387},{"Date":"\/Date(1323842400000)\/","Count":4,"TotalCount":2391},{"Date":"\/Date(1323928800000)\/","Count":1,"TotalCount":2392},{"Date":"\/Date(1324015200000)\/","Count":8,"TotalCount":2400},{"Date":"\/Date(1324101600000)\/","Count":6,"TotalCount":2406},{"Date":"\/Date(1324188000000)\/","Count":11,"TotalCount":2417},{"Date":"\/Date(1324620000000)\/","Count":12,"TotalCount":2429},{"Date":"\/Date(1324706400000)\/","Count":8,"TotalCount":2437},{"Date":"\/Date(1324792800000)\/","Count":4,"TotalCount":2441},{"Date":"\/Date(1324879200000)\/","Count":7,"TotalCount":2448},{"Date":"\/Date(1324965600000)\/","Count":2,"TotalCount":2450},{"Date":"\/Date(1325138400000)\/","Count":1,"TotalCount":2451},{"Date":"\/Date(1325224800000)\/","Count":6,"TotalCount":2457},{"Date":"\/Date(1325311200000)\/","Count":15,"TotalCount":2472},{"Date":"\/Date(1325397600000)\/","Count":5,"TotalCount":2477},{"Date":"\/Date(1325484000000)\/","Count":9,"TotalCount":2486},{"Date":"\/Date(1325570400000)\/","Count":1,"TotalCount":2487},{"Date":"\/Date(1325916000000)\/","Count":6,"TotalCount":2493},{"Date":"\/Date(1326002400000)\/","Count":1,"TotalCount":2494},{"Date":"\/Date(1326088800000)\/","Count":3,"TotalCount":2497},{"Date":"\/Date(1326175200000)\/","Count":1,"TotalCount":2498},{"Date":"\/Date(1326348000000)\/","Count":2,"TotalCount":2500},{"Date":"\/Date(1326434400000)\/","Count":3,"TotalCount":2503},{"Date":"\/Date(1326520800000)\/","Count":3,"TotalCount":2506},{"Date":"\/Date(1326607200000)\/","Count":5,"TotalCount":2511},{"Date":"\/Date(1326693600000)\/","Count":1,"TotalCount":2512},{"Date":"\/Date(1327039200000)\/","Count":2,"TotalCount":2514},{"Date":"\/Date(1327125600000)\/","Count":9,"TotalCount":2523},{"Date":"\/Date(1327212000000)\/","Count":26,"TotalCount":2549},{"Date":"\/Date(1327298400000)\/","Count":5,"TotalCount":2554},{"Date":"\/Date(1327384800000)\/","Count":5,"TotalCount":2559},{"Date":"\/Date(1327471200000)\/","Count":5,"TotalCount":2564},{"Date":"\/Date(1327557600000)\/","Count":3,"TotalCount":2567},{"Date":"\/Date(1327644000000)\/","Count":12,"TotalCount":2579},{"Date":"\/Date(1327730400000)\/","Count":18,"TotalCount":2597},{"Date":"\/Date(1327816800000)\/","Count":9,"TotalCount":2606},{"Date":"\/Date(1328076000000)\/","Count":1,"TotalCount":2607},{"Date":"\/Date(1328248800000)\/","Count":3,"TotalCount":2610},{"Date":"\/Date(1328421600000)\/","Count":4,"TotalCount":2614},{"Date":"\/Date(1328508000000)\/","Count":1,"TotalCount":2615},{"Date":"\/Date(1328594400000)\/","Count":3,"TotalCount":2618},{"Date":"\/Date(1328680800000)\/","Count":9,"TotalCount":2627},{"Date":"\/Date(1328853600000)\/","Count":8,"TotalCount":2635},{"Date":"\/Date(1328940000000)\/","Count":1,"TotalCount":2636},{"Date":"\/Date(1329458400000)\/","Count":1,"TotalCount":2637},{"Date":"\/Date(1329717600000)\/","Count":10,"TotalCount":2647},{"Date":"\/Date(1329890400000)\/","Count":1,"TotalCount":2648},{"Date":"\/Date(1329976800000)\/","Count":4,"TotalCount":2652},{"Date":"\/Date(1330063200000)\/","Count":19,"TotalCount":2671},{"Date":"\/Date(1330149600000)\/","Count":22,"TotalCount":2693},{"Date":"\/Date(1330236000000)\/","Count":19,"TotalCount":2712},{"Date":"\/Date(1330322400000)\/","Count":2,"TotalCount":2714},{"Date":"\/Date(1330668000000)\/","Count":16,"TotalCount":2730},{"Date":"\/Date(1330754400000)\/","Count":3,"TotalCount":2733},{"Date":"\/Date(1330840800000)\/","Count":29,"TotalCount":2762},{"Date":"\/Date(1330927200000)\/","Count":5,"TotalCount":2767},{"Date":"\/Date(1331013600000)\/","Count":2,"TotalCount":2769},{"Date":"\/Date(1331186400000)\/","Count":1,"TotalCount":2770},{"Date":"\/Date(1331272800000)\/","Count":6,"TotalCount":2776},{"Date":"\/Date(1331359200000)\/","Count":19,"TotalCount":2795},{"Date":"\/Date(1331528400000)\/","Count":2,"TotalCount":2797},{"Date":"\/Date(1331787600000)\/","Count":1,"TotalCount":2798},{"Date":"\/Date(1331874000000)\/","Count":3,"TotalCount":2801},{"Date":"\/Date(1331960400000)\/","Count":5,"TotalCount":2806},{"Date":"\/Date(1332046800000)\/","Count":8,"TotalCount":2814},{"Date":"\/Date(1332133200000)\/","Count":2,"TotalCount":2816},{"Date":"\/Date(1332306000000)\/","Count":1,"TotalCount":2817},{"Date":"\/Date(1332478800000)\/","Count":3,"TotalCount":2820},{"Date":"\/Date(1332565200000)\/","Count":2,"TotalCount":2822},{"Date":"\/Date(1332651600000)\/","Count":4,"TotalCount":2826},{"Date":"\/Date(1332824400000)\/","Count":1,"TotalCount":2827},{"Date":"\/Date(1332910800000)\/","Count":2,"TotalCount":2829},{"Date":"\/Date(1333083600000)\/","Count":1,"TotalCount":2830},{"Date":"\/Date(1333170000000)\/","Count":2,"TotalCount":2832},{"Date":"\/Date(1333256400000)\/","Count":1,"TotalCount":2833},{"Date":"\/Date(1333429200000)\/","Count":2,"TotalCount":2835},{"Date":"\/Date(1333602000000)\/","Count":1,"TotalCount":2836},{"Date":"\/Date(1333688400000)\/","Count":1,"TotalCount":2837},{"Date":"\/Date(1333774800000)\/","Count":6,"TotalCount":2843},{"Date":"\/Date(1333861200000)\/","Count":11,"TotalCount":2854},{"Date":"\/Date(1333947600000)\/","Count":1,"TotalCount":2855},{"Date":"\/Date(1334034000000)\/","Count":2,"TotalCount":2857},{"Date":"\/Date(1334120400000)\/","Count":6,"TotalCount":2863},{"Date":"\/Date(1334206800000)\/","Count":4,"TotalCount":2867},{"Date":"\/Date(1334293200000)\/","Count":9,"TotalCount":2876},{"Date":"\/Date(1334379600000)\/","Count":9,"TotalCount":2885},{"Date":"\/Date(1334466000000)\/","Count":11,"TotalCount":2896},{"Date":"\/Date(1334984400000)\/","Count":2,"TotalCount":2898},{"Date":"\/Date(1335070800000)\/","Count":5,"TotalCount":2903},{"Date":"\/Date(1335157200000)\/","Count":7,"TotalCount":2910},{"Date":"\/Date(1335589200000)\/","Count":3,"TotalCount":2913},{"Date":"\/Date(1335675600000)\/","Count":19,"TotalCount":2932},{"Date":"\/Date(1335848400000)\/","Count":10,"TotalCount":2942},{"Date":"\/Date(1336280400000)\/","Count":13,"TotalCount":2955},{"Date":"\/Date(1336885200000)\/","Count":2,"TotalCount":2957},{"Date":"\/Date(1337403600000)\/","Count":1,"TotalCount":2958},{"Date":"\/Date(1337490000000)\/","Count":1,"TotalCount":2959},{"Date":"\/Date(1337662800000)\/","Count":1,"TotalCount":2960},{"Date":"\/Date(1338008400000)\/","Count":2,"TotalCount":2962},{"Date":"\/Date(1338094800000)\/","Count":7,"TotalCount":2969},{"Date":"\/Date(1338181200000)\/","Count":9,"TotalCount":2978},{"Date":"\/Date(1338526800000)\/","Count":2,"TotalCount":2980},{"Date":"\/Date(1338613200000)\/","Count":4,"TotalCount":2984},{"Date":"\/Date(1338699600000)\/","Count":7,"TotalCount":2991},{"Date":"\/Date(1338872400000)\/","Count":1,"TotalCount":2992},{"Date":"\/Date(1338958800000)\/","Count":10,"TotalCount":3002},{"Date":"\/Date(1339131600000)\/","Count":3,"TotalCount":3005},{"Date":"\/Date(1339218000000)\/","Count":15,"TotalCount":3020},{"Date":"\/Date(1339304400000)\/","Count":14,"TotalCount":3034},{"Date":"\/Date(1339822800000)\/","Count":7,"TotalCount":3041},{"Date":"\/Date(1339909200000)\/","Count":3,"TotalCount":3044},{"Date":"\/Date(1339995600000)\/","Count":3,"TotalCount":3047},{"Date":"\/Date(1340168400000)\/","Count":3,"TotalCount":3050},{"Date":"\/Date(1340341200000)\/","Count":7,"TotalCount":3057},{"Date":"\/Date(1340427600000)\/","Count":3,"TotalCount":3060},{"Date":"\/Date(1340514000000)\/","Count":9,"TotalCount":3069},{"Date":"\/Date(1340773200000)\/","Count":3,"TotalCount":3072},{"Date":"\/Date(1340859600000)\/","Count":3,"TotalCount":3075},{"Date":"\/Date(1341032400000)\/","Count":9,"TotalCount":3084},{"Date":"\/Date(1341118800000)\/","Count":28,"TotalCount":3112},{"Date":"\/Date(1341205200000)\/","Count":2,"TotalCount":3114},{"Date":"\/Date(1341291600000)\/","Count":3,"TotalCount":3117},{"Date":"\/Date(1341378000000)\/","Count":14,"TotalCount":3131},{"Date":"\/Date(1341637200000)\/","Count":9,"TotalCount":3140},{"Date":"\/Date(1341723600000)\/","Count":5,"TotalCount":3145},{"Date":"\/Date(1341810000000)\/","Count":3,"TotalCount":3148},{"Date":"\/Date(1341896400000)\/","Count":5,"TotalCount":3153},{"Date":"\/Date(1341982800000)\/","Count":2,"TotalCount":3155},{"Date":"\/Date(1342069200000)\/","Count":3,"TotalCount":3158},{"Date":"\/Date(1343019600000)\/","Count":4,"TotalCount":3162},{"Date":"\/Date(1343106000000)\/","Count":4,"TotalCount":3166},{"Date":"\/Date(1343278800000)\/","Count":1,"TotalCount":3167},{"Date":"\/Date(1343451600000)\/","Count":5,"TotalCount":3172},{"Date":"\/Date(1343538000000)\/","Count":4,"TotalCount":3176},{"Date":"\/Date(1343624400000)\/","Count":1,"TotalCount":3177},{"Date":"\/Date(1343710800000)\/","Count":4,"TotalCount":3181},{"Date":"\/Date(1343797200000)\/","Count":2,"TotalCount":3183},{"Date":"\/Date(1343883600000)\/","Count":1,"TotalCount":3184},{"Date":"\/Date(1343970000000)\/","Count":5,"TotalCount":3189},{"Date":"\/Date(1344056400000)\/","Count":4,"TotalCount":3193},{"Date":"\/Date(1344142800000)\/","Count":2,"TotalCount":3195},{"Date":"\/Date(1344661200000)\/","Count":8,"TotalCount":3203},{"Date":"\/Date(1344747600000)\/","Count":9,"TotalCount":3212},{"Date":"\/Date(1345093200000)\/","Count":2,"TotalCount":3214},{"Date":"\/Date(1345352400000)\/","Count":1,"TotalCount":3215},{"Date":"\/Date(1345611600000)\/","Count":2,"TotalCount":3217},{"Date":"\/Date(1345870800000)\/","Count":6,"TotalCount":3223},{"Date":"\/Date(1345957200000)\/","Count":1,"TotalCount":3224},{"Date":"\/Date(1346389200000)\/","Count":1,"TotalCount":3225},{"Date":"\/Date(1346475600000)\/","Count":2,"TotalCount":3227},{"Date":"\/Date(1346562000000)\/","Count":3,"TotalCount":3230},{"Date":"\/Date(1346648400000)\/","Count":2,"TotalCount":3232},{"Date":"\/Date(1346907600000)\/","Count":1,"TotalCount":3233},{"Date":"\/Date(1346994000000)\/","Count":1,"TotalCount":3234},{"Date":"\/Date(1347080400000)\/","Count":6,"TotalCount":3240},{"Date":"\/Date(1347166800000)\/","Count":1,"TotalCount":3241},{"Date":"\/Date(1347339600000)\/","Count":2,"TotalCount":3243},{"Date":"\/Date(1347512400000)\/","Count":2,"TotalCount":3245},{"Date":"\/Date(1347685200000)\/","Count":8,"TotalCount":3253},{"Date":"\/Date(1347771600000)\/","Count":7,"TotalCount":3260},{"Date":"\/Date(1347858000000)\/","Count":7,"TotalCount":3267},{"Date":"\/Date(1348462800000)\/","Count":10,"TotalCount":3277},{"Date":"\/Date(1348635600000)\/","Count":6,"TotalCount":3283},{"Date":"\/Date(1348808400000)\/","Count":2,"TotalCount":3285},{"Date":"\/Date(1348894800000)\/","Count":9,"TotalCount":3294},{"Date":"\/Date(1348981200000)\/","Count":8,"TotalCount":3302},{"Date":"\/Date(1349154000000)\/","Count":1,"TotalCount":3303},{"Date":"\/Date(1349240400000)\/","Count":1,"TotalCount":3304},{"Date":"\/Date(1349326800000)\/","Count":1,"TotalCount":3305},{"Date":"\/Date(1349413200000)\/","Count":6,"TotalCount":3311},{"Date":"\/Date(1349499600000)\/","Count":2,"TotalCount":3313},{"Date":"\/Date(1349586000000)\/","Count":4,"TotalCount":3317},{"Date":"\/Date(1349758800000)\/","Count":1,"TotalCount":3318},{"Date":"\/Date(1349845200000)\/","Count":1,"TotalCount":3319},{"Date":"\/Date(1349931600000)\/","Count":6,"TotalCount":3325},{"Date":"\/Date(1350018000000)\/","Count":1,"TotalCount":3326},{"Date":"\/Date(1350104400000)\/","Count":2,"TotalCount":3328},{"Date":"\/Date(1350190800000)\/","Count":10,"TotalCount":3338},{"Date":"\/Date(1350450000000)\/","Count":1,"TotalCount":3339},{"Date":"\/Date(1350536400000)\/","Count":5,"TotalCount":3344},{"Date":"\/Date(1350709200000)\/","Count":6,"TotalCount":3350},{"Date":"\/Date(1350795600000)\/","Count":4,"TotalCount":3354},{"Date":"\/Date(1351227600000)\/","Count":4,"TotalCount":3358},{"Date":"\/Date(1351314000000)\/","Count":26,"TotalCount":3384},{"Date":"\/Date(1351400400000)\/","Count":12,"TotalCount":3396},{"Date":"\/Date(1351746000000)\/","Count":1,"TotalCount":3397},{"Date":"\/Date(1351832400000)\/","Count":1,"TotalCount":3398},{"Date":"\/Date(1351918800000)\/","Count":1,"TotalCount":3399},{"Date":"\/Date(1352005200000)\/","Count":8,"TotalCount":3407},{"Date":"\/Date(1352095200000)\/","Count":3,"TotalCount":3410},{"Date":"\/Date(1352268000000)\/","Count":1,"TotalCount":3411},{"Date":"\/Date(1352354400000)\/","Count":1,"TotalCount":3412},{"Date":"\/Date(1352440800000)\/","Count":1,"TotalCount":3413},{"Date":"\/Date(1352527200000)\/","Count":7,"TotalCount":3420},{"Date":"\/Date(1352613600000)\/","Count":22,"TotalCount":3442},{"Date":"\/Date(1352700000000)\/","Count":7,"TotalCount":3449},{"Date":"\/Date(1352786400000)\/","Count":1,"TotalCount":3450},{"Date":"\/Date(1352872800000)\/","Count":3,"TotalCount":3453},{"Date":"\/Date(1352959200000)\/","Count":4,"TotalCount":3457},{"Date":"\/Date(1353045600000)\/","Count":4,"TotalCount":3461},{"Date":"\/Date(1353132000000)\/","Count":11,"TotalCount":3472},{"Date":"\/Date(1353218400000)\/","Count":7,"TotalCount":3479},{"Date":"\/Date(1353304800000)\/","Count":15,"TotalCount":3494},{"Date":"\/Date(1353391200000)\/","Count":7,"TotalCount":3501},{"Date":"\/Date(1353477600000)\/","Count":6,"TotalCount":3507},{"Date":"\/Date(1353564000000)\/","Count":5,"TotalCount":3512},{"Date":"\/Date(1353650400000)\/","Count":14,"TotalCount":3526},{"Date":"\/Date(1353736800000)\/","Count":14,"TotalCount":3540},{"Date":"\/Date(1353823200000)\/","Count":8,"TotalCount":3548},{"Date":"\/Date(1353909600000)\/","Count":1,"TotalCount":3549},{"Date":"\/Date(1353996000000)\/","Count":1,"TotalCount":3550},{"Date":"\/Date(1354168800000)\/","Count":1,"TotalCount":3551},{"Date":"\/Date(1354255200000)\/","Count":3,"TotalCount":3554},{"Date":"\/Date(1354341600000)\/","Count":18,"TotalCount":3572},{"Date":"\/Date(1354428000000)\/","Count":9,"TotalCount":3581},{"Date":"\/Date(1354514400000)\/","Count":1,"TotalCount":3582},{"Date":"\/Date(1354600800000)\/","Count":2,"TotalCount":3584},{"Date":"\/Date(1354687200000)\/","Count":3,"TotalCount":3587},{"Date":"\/Date(1354773600000)\/","Count":3,"TotalCount":3590},{"Date":"\/Date(1354860000000)\/","Count":2,"TotalCount":3592},{"Date":"\/Date(1354946400000)\/","Count":15,"TotalCount":3607},{"Date":"\/Date(1355032800000)\/","Count":7,"TotalCount":3614},{"Date":"\/Date(1355119200000)\/","Count":2,"TotalCount":3616},{"Date":"\/Date(1355205600000)\/","Count":5,"TotalCount":3621},{"Date":"\/Date(1355292000000)\/","Count":2,"TotalCount":3623},{"Date":"\/Date(1355378400000)\/","Count":4,"TotalCount":3627},{"Date":"\/Date(1355464800000)\/","Count":4,"TotalCount":3631},{"Date":"\/Date(1355551200000)\/","Count":12,"TotalCount":3643},{"Date":"\/Date(1355637600000)\/","Count":11,"TotalCount":3654},{"Date":"\/Date(1355724000000)\/","Count":1,"TotalCount":3655},{"Date":"\/Date(1355810400000)\/","Count":1,"TotalCount":3656},{"Date":"\/Date(1355896800000)\/","Count":17,"TotalCount":3673},{"Date":"\/Date(1355983200000)\/","Count":5,"TotalCount":3678},{"Date":"\/Date(1356069600000)\/","Count":5,"TotalCount":3683},{"Date":"\/Date(1356156000000)\/","Count":1,"TotalCount":3684},{"Date":"\/Date(1356242400000)\/","Count":1,"TotalCount":3685},{"Date":"\/Date(1356328800000)\/","Count":13,"TotalCount":3698},{"Date":"\/Date(1356415200000)\/","Count":6,"TotalCount":3704},{"Date":"\/Date(1356501600000)\/","Count":1,"TotalCount":3705},{"Date":"\/Date(1356588000000)\/","Count":2,"TotalCount":3707},{"Date":"\/Date(1356674400000)\/","Count":5,"TotalCount":3712},{"Date":"\/Date(1356760800000)\/","Count":3,"TotalCount":3715},{"Date":"\/Date(1356847200000)\/","Count":1,"TotalCount":3716},{"Date":"\/Date(1356933600000)\/","Count":1,"TotalCount":3717},{"Date":"\/Date(1357020000000)\/","Count":13,"TotalCount":3730},{"Date":"\/Date(1357365600000)\/","Count":6,"TotalCount":3736},{"Date":"\/Date(1357452000000)\/","Count":12,"TotalCount":3748},{"Date":"\/Date(1357538400000)\/","Count":1,"TotalCount":3749},{"Date":"\/Date(1357711200000)\/","Count":1,"TotalCount":3750},{"Date":"\/Date(1357884000000)\/","Count":2,"TotalCount":3752},{"Date":"\/Date(1357970400000)\/","Count":3,"TotalCount":3755},{"Date":"\/Date(1358056800000)\/","Count":15,"TotalCount":3770},{"Date":"\/Date(1358229600000)\/","Count":1,"TotalCount":3771},{"Date":"\/Date(1358316000000)\/","Count":2,"TotalCount":3773},{"Date":"\/Date(1358402400000)\/","Count":1,"TotalCount":3774},{"Date":"\/Date(1358488800000)\/","Count":1,"TotalCount":3775},{"Date":"\/Date(1358575200000)\/","Count":15,"TotalCount":3790},{"Date":"\/Date(1358661600000)\/","Count":15,"TotalCount":3805},{"Date":"\/Date(1358748000000)\/","Count":13,"TotalCount":3818},{"Date":"\/Date(1359007200000)\/","Count":1,"TotalCount":3819},{"Date":"\/Date(1359180000000)\/","Count":4,"TotalCount":3823},{"Date":"\/Date(1359266400000)\/","Count":17,"TotalCount":3840},{"Date":"\/Date(1359525600000)\/","Count":34,"TotalCount":3874},{"Date":"\/Date(1359871200000)\/","Count":14,"TotalCount":3888},{"Date":"\/Date(1360044000000)\/","Count":3,"TotalCount":3891},{"Date":"\/Date(1360130400000)\/","Count":3,"TotalCount":3894},{"Date":"\/Date(1360216800000)\/","Count":3,"TotalCount":3897},{"Date":"\/Date(1360389600000)\/","Count":7,"TotalCount":3904},{"Date":"\/Date(1360476000000)\/","Count":23,"TotalCount":3927},{"Date":"\/Date(1360648800000)\/","Count":1,"TotalCount":3928},{"Date":"\/Date(1360821600000)\/","Count":3,"TotalCount":3931},{"Date":"\/Date(1360994400000)\/","Count":2,"TotalCount":3933},{"Date":"\/Date(1361080800000)\/","Count":18,"TotalCount":3951},{"Date":"\/Date(1361512800000)\/","Count":5,"TotalCount":3956},{"Date":"\/Date(1361599200000)\/","Count":5,"TotalCount":3961},{"Date":"\/Date(1361685600000)\/","Count":7,"TotalCount":3968},{"Date":"\/Date(1361858400000)\/","Count":2,"TotalCount":3970},{"Date":"\/Date(1361944800000)\/","Count":6,"TotalCount":3976},{"Date":"\/Date(1362031200000)\/","Count":6,"TotalCount":3982},{"Date":"\/Date(1362117600000)\/","Count":11,"TotalCount":3993},{"Date":"\/Date(1362204000000)\/","Count":11,"TotalCount":4004},{"Date":"\/Date(1362290400000)\/","Count":7,"TotalCount":4011},{"Date":"\/Date(1362376800000)\/","Count":3,"TotalCount":4014},{"Date":"\/Date(1362463200000)\/","Count":5,"TotalCount":4019},{"Date":"\/Date(1362636000000)\/","Count":3,"TotalCount":4022},{"Date":"\/Date(1362722400000)\/","Count":40,"TotalCount":4062},{"Date":"\/Date(1362808800000)\/","Count":9,"TotalCount":4071},{"Date":"\/Date(1362895200000)\/","Count":5,"TotalCount":4076},{"Date":"\/Date(1362978000000)\/","Count":1,"TotalCount":4077},{"Date":"\/Date(1363150800000)\/","Count":2,"TotalCount":4079},{"Date":"\/Date(1363323600000)\/","Count":5,"TotalCount":4084},{"Date":"\/Date(1363410000000)\/","Count":7,"TotalCount":4091},{"Date":"\/Date(1363496400000)\/","Count":1,"TotalCount":4092},{"Date":"\/Date(1363582800000)\/","Count":1,"TotalCount":4093},{"Date":"\/Date(1363669200000)\/","Count":6,"TotalCount":4099},{"Date":"\/Date(1363755600000)\/","Count":8,"TotalCount":4107},{"Date":"\/Date(1363842000000)\/","Count":7,"TotalCount":4114},{"Date":"\/Date(1363928400000)\/","Count":5,"TotalCount":4119},{"Date":"\/Date(1364014800000)\/","Count":3,"TotalCount":4122},{"Date":"\/Date(1364101200000)\/","Count":6,"TotalCount":4128},{"Date":"\/Date(1364274000000)\/","Count":2,"TotalCount":4130},{"Date":"\/Date(1364360400000)\/","Count":1,"TotalCount":4131},{"Date":"\/Date(1364446800000)\/","Count":5,"TotalCount":4136},{"Date":"\/Date(1364533200000)\/","Count":2,"TotalCount":4138},{"Date":"\/Date(1364619600000)\/","Count":13,"TotalCount":4151},{"Date":"\/Date(1364706000000)\/","Count":16,"TotalCount":4167},{"Date":"\/Date(1364878800000)\/","Count":5,"TotalCount":4172},{"Date":"\/Date(1364965200000)\/","Count":1,"TotalCount":4173},{"Date":"\/Date(1365051600000)\/","Count":6,"TotalCount":4179},{"Date":"\/Date(1365138000000)\/","Count":5,"TotalCount":4184},{"Date":"\/Date(1365224400000)\/","Count":2,"TotalCount":4186},{"Date":"\/Date(1365310800000)\/","Count":3,"TotalCount":4189},{"Date":"\/Date(1365397200000)\/","Count":1,"TotalCount":4190},{"Date":"\/Date(1365656400000)\/","Count":7,"TotalCount":4197},{"Date":"\/Date(1365742800000)\/","Count":1,"TotalCount":4198},{"Date":"\/Date(1365829200000)\/","Count":5,"TotalCount":4203},{"Date":"\/Date(1365915600000)\/","Count":8,"TotalCount":4211},{"Date":"\/Date(1366002000000)\/","Count":2,"TotalCount":4213},{"Date":"\/Date(1366088400000)\/","Count":1,"TotalCount":4214},{"Date":"\/Date(1366174800000)\/","Count":3,"TotalCount":4217},{"Date":"\/Date(1366261200000)\/","Count":2,"TotalCount":4219},{"Date":"\/Date(1366347600000)\/","Count":2,"TotalCount":4221},{"Date":"\/Date(1366434000000)\/","Count":7,"TotalCount":4228},{"Date":"\/Date(1366520400000)\/","Count":7,"TotalCount":4235},{"Date":"\/Date(1366606800000)\/","Count":4,"TotalCount":4239},{"Date":"\/Date(1366693200000)\/","Count":1,"TotalCount":4240},{"Date":"\/Date(1366779600000)\/","Count":1,"TotalCount":4241},{"Date":"\/Date(1366866000000)\/","Count":2,"TotalCount":4243},{"Date":"\/Date(1366952400000)\/","Count":3,"TotalCount":4246},{"Date":"\/Date(1367038800000)\/","Count":12,"TotalCount":4258},{"Date":"\/Date(1367125200000)\/","Count":13,"TotalCount":4271},{"Date":"\/Date(1367211600000)\/","Count":2,"TotalCount":4273},{"Date":"\/Date(1367298000000)\/","Count":4,"TotalCount":4277},{"Date":"\/Date(1367384400000)\/","Count":2,"TotalCount":4279},{"Date":"\/Date(1367470800000)\/","Count":19,"TotalCount":4298}],"AccomplishmentsByYearMonth":[{"YearMonth":"\/Date(1214888400000)\/","Count":9},{"YearMonth":"\/Date(1217566800000)\/","Count":45},{"YearMonth":"\/Date(1222837200000)\/","Count":32},{"YearMonth":"\/Date(1225515600000)\/","Count":30},{"YearMonth":"\/Date(1228111200000)\/","Count":163},{"YearMonth":"\/Date(1230789600000)\/","Count":51},{"YearMonth":"\/Date(1233468000000)\/","Count":60},{"YearMonth":"\/Date(1235887200000)\/","Count":71},{"YearMonth":"\/Date(1238562000000)\/","Count":52},{"YearMonth":"\/Date(1241154000000)\/","Count":96},{"YearMonth":"\/Date(1243832400000)\/","Count":42},{"YearMonth":"\/Date(1246424400000)\/","Count":25},{"YearMonth":"\/Date(1249102800000)\/","Count":52},{"YearMonth":"\/Date(1251781200000)\/","Count":91},{"YearMonth":"\/Date(1254373200000)\/","Count":41},{"YearMonth":"\/Date(1257051600000)\/","Count":12},{"YearMonth":"\/Date(1259647200000)\/","Count":68},{"YearMonth":"\/Date(1262325600000)\/","Count":77},{"YearMonth":"\/Date(1265004000000)\/","Count":22},{"YearMonth":"\/Date(1267423200000)\/","Count":38},{"YearMonth":"\/Date(1270098000000)\/","Count":104},{"YearMonth":"\/Date(1272690000000)\/","Count":33},{"YearMonth":"\/Date(1275368400000)\/","Count":19},{"YearMonth":"\/Date(1277960400000)\/","Count":1},{"YearMonth":"\/Date(1280638800000)\/","Count":21},{"YearMonth":"\/Date(1283317200000)\/","Count":45},{"YearMonth":"\/Date(1285909200000)\/","Count":41},{"YearMonth":"\/Date(1288587600000)\/","Count":18},{"YearMonth":"\/Date(1291183200000)\/","Count":8},{"YearMonth":"\/Date(1293861600000)\/","Count":5},{"YearMonth":"\/Date(1296540000000)\/","Count":48},{"YearMonth":"\/Date(1298959200000)\/","Count":43},{"YearMonth":"\/Date(1301634000000)\/","Count":34},{"YearMonth":"\/Date(1304226000000)\/","Count":87},{"YearMonth":"\/Date(1306904400000)\/","Count":117},{"YearMonth":"\/Date(1309496400000)\/","Count":65},{"YearMonth":"\/Date(1312174800000)\/","Count":104},{"YearMonth":"\/Date(1314853200000)\/","Count":98},{"YearMonth":"\/Date(1317445200000)\/","Count":177},{"YearMonth":"\/Date(1320123600000)\/","Count":190},{"YearMonth":"\/Date(1322719200000)\/","Count":137},{"YearMonth":"\/Date(1325397600000)\/","Count":134},{"YearMonth":"\/Date(1328076000000)\/","Count":108},{"YearMonth":"\/Date(1330581600000)\/","Count":118},{"YearMonth":"\/Date(1333256400000)\/","Count":100},{"YearMonth":"\/Date(1335848400000)\/","Count":46},{"YearMonth":"\/Date(1338526800000)\/","Count":106},{"YearMonth":"\/Date(1341118800000)\/","Count":97},{"YearMonth":"\/Date(1343797200000)\/","Count":44},{"YearMonth":"\/Date(1346475600000)\/","Count":77},{"YearMonth":"\/Date(1349067600000)\/","Count":94},{"YearMonth":"\/Date(1351746000000)\/","Count":158},{"YearMonth":"\/Date(1354341600000)\/","Count":163},{"YearMonth":"\/Date(1357020000000)\/","Count":157},{"YearMonth":"\/Date(1359698400000)\/","Count":108},{"YearMonth":"\/Date(1362117600000)\/","Count":185},{"YearMonth":"\/Date(1364792400000)\/","Count":110},{"YearMonth":"\/Date(1367384400000)\/","Count":21}],"AccomplishmentsByDayOfWeek":[{"DayOfWeek":0,"DayOfWeekString":"Sunday","Count":1172},{"DayOfWeek":1,"DayOfWeekString":"Monday","Count":336},{"DayOfWeek":2,"DayOfWeekString":"Tuesday","Count":277},{"DayOfWeek":3,"DayOfWeekString":"Wednesday","Count":307},{"DayOfWeek":4,"DayOfWeekString":"Thursday","Count":360},{"DayOfWeek":5,"DayOfWeekString":"Friday","Count":742},{"DayOfWeek":6,"DayOfWeekString":"Saturday","Count":1104}],"AccomplishmentsByHour":[{"Hour":0,"Count":8},{"Hour":1,"Count":5},{"Hour":2,"Count":2},{"Hour":3,"Count":2},{"Hour":4,"Count":7},{"Hour":5,"Count":12},{"Hour":6,"Count":80},{"Hour":7,"Count":80},{"Hour":8,"Count":142},{"Hour":9,"Count":169},{"Hour":10,"Count":222},{"Hour":11,"Count":219},{"Hour":12,"Count":227},{"Hour":13,"Count":239},{"Hour":14,"Count":219},{"Hour":15,"Count":249},{"Hour":16,"Count":271},{"Hour":17,"Count":314},{"Hour":18,"Count":278},{"Hour":19,"Count":317},{"Hour":20,"Count":491},{"Hour":21,"Count":485},{"Hour":22,"Count":197},{"Hour":23,"Count":63}],"AccomplishmentsByDayOfWeekAndHour":[{"DayOfWeek":0,"DayOfWeekString":"Sunday","Hour":1,"Count":1},{"DayOfWeek":0,"DayOfWeekString":"Sunday","Hour":4,"Count":6},{"DayOfWeek":0,"DayOfWeekString":"Sunday","Hour":5,"Count":2},{"DayOfWeek":0,"DayOfWeekString":"Sunday","Hour":6,"Count":16},{"DayOfWeek":0,"DayOfWeekString":"Sunday","Hour":7,"Count":29},{"DayOfWeek":0,"DayOfWeekString":"Sunday","Hour":8,"Count":56},{"DayOfWeek":0,"DayOfWeekString":"Sunday","Hour":9,"Count":73},{"DayOfWeek":0,"DayOfWeekString":"Sunday","Hour":10,"Count":86},{"DayOfWeek":0,"DayOfWeekString":"Sunday","Hour":11,"Count":89},{"DayOfWeek":0,"DayOfWeekString":"Sunday","Hour":12,"Count":96},{"DayOfWeek":0,"DayOfWeekString":"Sunday","Hour":13,"Count":90},{"DayOfWeek":0,"DayOfWeekString":"Sunday","Hour":14,"Count":88},{"DayOfWeek":0,"DayOfWeekString":"Sunday","Hour":15,"Count":93},{"DayOfWeek":0,"DayOfWeekString":"Sunday","Hour":16,"Count":87},{"DayOfWeek":0,"DayOfWeekString":"Sunday","Hour":17,"Count":92},{"DayOfWeek":0,"DayOfWeekString":"Sunday","Hour":18,"Count":80},{"DayOfWeek":0,"DayOfWeekString":"Sunday","Hour":19,"Count":60},{"DayOfWeek":0,"DayOfWeekString":"Sunday","Hour":20,"Count":57},{"DayOfWeek":0,"DayOfWeekString":"Sunday","Hour":21,"Count":46},{"DayOfWeek":0,"DayOfWeekString":"Sunday","Hour":22,"Count":20},{"DayOfWeek":0,"DayOfWeekString":"Sunday","Hour":23,"Count":5},{"DayOfWeek":1,"DayOfWeekString":"Monday","Hour":0,"Count":11},{"DayOfWeek":1,"DayOfWeekString":"Monday","Hour":4,"Count":1},{"DayOfWeek":1,"DayOfWeekString":"Monday","Hour":6,"Count":6},{"DayOfWeek":1,"DayOfWeekString":"Monday","Hour":7,"Count":2},{"DayOfWeek":1,"DayOfWeekString":"Monday","Hour":8,"Count":12},{"DayOfWeek":1,"DayOfWeekString":"Monday","Hour":9,"Count":14},{"DayOfWeek":1,"DayOfWeekString":"Monday","Hour":10,"Count":7},{"DayOfWeek":1,"DayOfWeekString":"Monday","Hour":11,"Count":22},{"DayOfWeek":1,"DayOfWeekString":"Monday","Hour":12,"Count":14},{"DayOfWeek":1,"DayOfWeekString":"Monday","Hour":13,"Count":11},{"DayOfWeek":1,"DayOfWeekString":"Monday","Hour":14,"Count":6},{"DayOfWeek":1,"DayOfWeekString":"Monday","Hour":15,"Count":11},{"DayOfWeek":1,"DayOfWeekString":"Monday","Hour":16,"Count":7},{"DayOfWeek":1,"DayOfWeekString":"Monday","Hour":17,"Count":17},{"DayOfWeek":1,"DayOfWeekString":"Monday","Hour":18,"Count":9},{"DayOfWeek":1,"DayOfWeekString":"Monday","Hour":19,"Count":32},{"DayOfWeek":1,"DayOfWeekString":"Monday","Hour":20,"Count":70},{"DayOfWeek":1,"DayOfWeekString":"Monday","Hour":21,"Count":60},{"DayOfWeek":1,"DayOfWeekString":"Monday","Hour":22,"Count":31},{"DayOfWeek":1,"DayOfWeekString":"Monday","Hour":23,"Count":4},{"DayOfWeek":2,"DayOfWeekString":"Tuesday","Hour":5,"Count":1},{"DayOfWeek":2,"DayOfWeekString":"Tuesday","Hour":6,"Count":7},{"DayOfWeek":2,"DayOfWeekString":"Tuesday","Hour":7,"Count":7},{"DayOfWeek":2,"DayOfWeekString":"Tuesday","Hour":8,"Count":12},{"DayOfWeek":2,"DayOfWeekString":"Tuesday","Hour":9,"Count":5},{"DayOfWeek":2,"DayOfWeekString":"Tuesday","Hour":10,"Count":8},{"DayOfWeek":2,"DayOfWeekString":"Tuesday","Hour":11,"Count":8},{"DayOfWeek":2,"DayOfWeekString":"Tuesday","Hour":12,"Count":8},{"DayOfWeek":2,"DayOfWeekString":"Tuesday","Hour":13,"Count":8},{"DayOfWeek":2,"DayOfWeekString":"Tuesday","Hour":14,"Count":6},{"DayOfWeek":2,"DayOfWeekString":"Tuesday","Hour":15,"Count":11},{"DayOfWeek":2,"DayOfWeekString":"Tuesday","Hour":16,"Count":13},{"DayOfWeek":2,"DayOfWeekString":"Tuesday","Hour":17,"Count":11},{"DayOfWeek":2,"DayOfWeekString":"Tuesday","Hour":18,"Count":3},{"DayOfWeek":2,"DayOfWeekString":"Tuesday","Hour":19,"Count":14},{"DayOfWeek":2,"DayOfWeekString":"Tuesday","Hour":20,"Count":61},{"DayOfWeek":2,"DayOfWeekString":"Tuesday","Hour":21,"Count":67},{"DayOfWeek":2,"DayOfWeekString":"Tuesday","Hour":22,"Count":20},{"DayOfWeek":2,"DayOfWeekString":"Tuesday","Hour":23,"Count":7},{"DayOfWeek":3,"DayOfWeekString":"Wednesday","Hour":5,"Count":1},{"DayOfWeek":3,"DayOfWeekString":"Wednesday","Hour":6,"Count":32},{"DayOfWeek":3,"DayOfWeekString":"Wednesday","Hour":7,"Count":12},{"DayOfWeek":3,"DayOfWeekString":"Wednesday","Hour":8,"Count":13},{"DayOfWeek":3,"DayOfWeekString":"Wednesday","Hour":9,"Count":2},{"DayOfWeek":3,"DayOfWeekString":"Wednesday","Hour":10,"Count":2},{"DayOfWeek":3,"DayOfWeekString":"Wednesday","Hour":11,"Count":2},{"DayOfWeek":3,"DayOfWeekString":"Wednesday","Hour":12,"Count":2},{"DayOfWeek":3,"DayOfWeekString":"Wednesday","Hour":14,"Count":7},{"DayOfWeek":3,"DayOfWeekString":"Wednesday","Hour":15,"Count":4},{"DayOfWeek":3,"DayOfWeekString":"Wednesday","Hour":16,"Count":4},{"DayOfWeek":3,"DayOfWeekString":"Wednesday","Hour":17,"Count":5},{"DayOfWeek":3,"DayOfWeekString":"Wednesday","Hour":18,"Count":5},{"DayOfWeek":3,"DayOfWeekString":"Wednesday","Hour":19,"Count":28},{"DayOfWeek":3,"DayOfWeekString":"Wednesday","Hour":20,"Count":69},{"DayOfWeek":3,"DayOfWeekString":"Wednesday","Hour":21,"Count":87},{"DayOfWeek":3,"DayOfWeekString":"Wednesday","Hour":22,"Count":27},{"DayOfWeek":3,"DayOfWeekString":"Wednesday","Hour":23,"Count":5},{"DayOfWeek":4,"DayOfWeekString":"Thursday","Hour":2,"Count":2},{"DayOfWeek":4,"DayOfWeekString":"Thursday","Hour":3,"Count":2},{"DayOfWeek":4,"DayOfWeekString":"Thursday","Hour":5,"Count":1},{"DayOfWeek":4,"DayOfWeekString":"Thursday","Hour":6,"Count":14},{"DayOfWeek":4,"DayOfWeekString":"Thursday","Hour":7,"Count":8},{"DayOfWeek":4,"DayOfWeekString":"Thursday","Hour":8,"Count":8},{"DayOfWeek":4,"DayOfWeekString":"Thursday","Hour":9,"Count":5},{"DayOfWeek":4,"DayOfWeekString":"Thursday","Hour":10,"Count":15},{"DayOfWeek":4,"DayOfWeekString":"Thursday","Hour":11,"Count":10},{"DayOfWeek":4,"DayOfWeekString":"Thursday","Hour":12,"Count":6},{"DayOfWeek":4,"DayOfWeekString":"Thursday","Hour":13,"Count":3},{"DayOfWeek":4,"DayOfWeekString":"Thursday","Hour":14,"Count":10},{"DayOfWeek":4,"DayOfWeekString":"Thursday","Hour":15,"Count":6},{"DayOfWeek":4,"DayOfWeekString":"Thursday","Hour":16,"Count":12},{"DayOfWeek":4,"DayOfWeekString":"Thursday","Hour":17,"Count":15},{"DayOfWeek":4,"DayOfWeekString":"Thursday","Hour":18,"Count":18},{"DayOfWeek":4,"DayOfWeekString":"Thursday","Hour":19,"Count":41},{"DayOfWeek":4,"DayOfWeekString":"Thursday","Hour":20,"Count":70},{"DayOfWeek":4,"DayOfWeekString":"Thursday","Hour":21,"Count":77},{"DayOfWeek":4,"DayOfWeekString":"Thursday","Hour":22,"Count":31},{"DayOfWeek":4,"DayOfWeekString":"Thursday","Hour":23,"Count":6},{"DayOfWeek":5,"DayOfWeekString":"Friday","Hour":0,"Count":2},{"DayOfWeek":5,"DayOfWeekString":"Friday","Hour":5,"Count":4},{"DayOfWeek":5,"DayOfWeekString":"Friday","Hour":6,"Count":3},{"DayOfWeek":5,"DayOfWeekString":"Friday","Hour":7,"Count":4},{"DayOfWeek":5,"DayOfWeekString":"Friday","Hour":8,"Count":11},{"DayOfWeek":5,"DayOfWeekString":"Friday","Hour":9,"Count":18},{"DayOfWeek":5,"DayOfWeekString":"Friday","Hour":10,"Count":30},{"DayOfWeek":5,"DayOfWeekString":"Friday","Hour":11,"Count":18},{"DayOfWeek":5,"DayOfWeekString":"Friday","Hour":12,"Count":19},{"DayOfWeek":5,"DayOfWeekString":"Friday","Hour":13,"Count":21},{"DayOfWeek":5,"DayOfWeekString":"Friday","Hour":14,"Count":35},{"DayOfWeek":5,"DayOfWeekString":"Friday","Hour":15,"Count":53},{"DayOfWeek":5,"DayOfWeekString":"Friday","Hour":16,"Count":59},{"DayOfWeek":5,"DayOfWeekString":"Friday","Hour":17,"Count":79},{"DayOfWeek":5,"DayOfWeekString":"Friday","Hour":18,"Count":54},{"DayOfWeek":5,"DayOfWeekString":"Friday","Hour":19,"Count":62},{"DayOfWeek":5,"DayOfWeekString":"Friday","Hour":20,"Count":103},{"DayOfWeek":5,"DayOfWeekString":"Friday","Hour":21,"Count":98},{"DayOfWeek":5,"DayOfWeekString":"Friday","Hour":22,"Count":46},{"DayOfWeek":5,"DayOfWeekString":"Friday","Hour":23,"Count":23},{"DayOfWeek":6,"DayOfWeekString":"Saturday","Hour":0,"Count":6},{"DayOfWeek":6,"DayOfWeekString":"Saturday","Hour":1,"Count":4},{"DayOfWeek":6,"DayOfWeekString":"Saturday","Hour":5,"Count":3},{"DayOfWeek":6,"DayOfWeekString":"Saturday","Hour":6,"Count":2},{"DayOfWeek":6,"DayOfWeekString":"Saturday","Hour":7,"Count":18},{"DayOfWeek":6,"DayOfWeekString":"Saturday","Hour":8,"Count":30},{"DayOfWeek":6,"DayOfWeekString":"Saturday","Hour":9,"Count":52},{"DayOfWeek":6,"DayOfWeekString":"Saturday","Hour":10,"Count":74},{"DayOfWeek":6,"DayOfWeekString":"Saturday","Hour":11,"Count":70},{"DayOfWeek":6,"DayOfWeekString":"Saturday","Hour":12,"Count":82},{"DayOfWeek":6,"DayOfWeekString":"Saturday","Hour":13,"Count":106},{"DayOfWeek":6,"DayOfWeekString":"Saturday","Hour":14,"Count":67},{"DayOfWeek":6,"DayOfWeekString":"Saturday","Hour":15,"Count":71},{"DayOfWeek":6,"DayOfWeekString":"Saturday","Hour":16,"Count":89},{"DayOfWeek":6,"DayOfWeekString":"Saturday","Hour":17,"Count":95},{"DayOfWeek":6,"DayOfWeekString":"Saturday","Hour":18,"Count":109},{"DayOfWeek":6,"DayOfWeekString":"Saturday","Hour":19,"Count":80},{"DayOfWeek":6,"DayOfWeekString":"Saturday","Hour":20,"Count":61},{"DayOfWeek":6,"DayOfWeekString":"Saturday","Hour":21,"Count":50},{"DayOfWeek":6,"DayOfWeekString":"Saturday","Hour":22,"Count":22},{"DayOfWeek":6,"DayOfWeekString":"Saturday","Hour":23,"Count":13}],"AccomplishmentsByType":[{"Type":"0","Earned":2,"Unearned":30,"Total":32},{"Type":"1","Earned":0,"Unearned":2,"Total":2},{"Type":"10","Earned":479,"Unearned":276,"Total":755},{"Type":"100","Earned":26,"Unearned":24,"Total":50},{"Type":"110","Earned":0,"Unearned":1,"Total":1},{"Type":"125","Earned":5,"Unearned":3,"Total":8},{"Type":"140","Earned":1,"Unearned":1,"Total":2},{"Type":"15","Earned":164,"Unearned":216,"Total":380},{"Type":"150","Earned":3,"Unearned":3,"Total":6},{"Type":"20","Earned":319,"Unearned":340,"Total":659},{"Type":"200","Earned":1,"Unearned":6,"Total":7},{"Type":"25","Earned":82,"Unearned":140,"Total":222},{"Type":"250","Earned":0,"Unearned":1,"Total":1},{"Type":"30","Earned":118,"Unearned":236,"Total":354},{"Type":"35","Earned":4,"Unearned":8,"Total":12},{"Type":"40","Earned":29,"Unearned":42,"Total":71},{"Type":"45","Earned":2,"Unearned":7,"Total":9},{"Type":"49","Earned":1,"Unearned":0,"Total":1},{"Type":"5","Earned":141,"Unearned":93,"Total":234},{"Type":"50","Earned":47,"Unearned":106,"Total":153},{"Type":"60","Earned":5,"Unearned":5,"Total":10},{"Type":"70","Earned":2,"Unearned":3,"Total":5},{"Type":"75","Earned":6,"Unearned":16,"Total":22},{"Type":"80","Earned":1,"Unearned":10,"Total":11},{"Type":"90","Earned":0,"Unearned":2,"Total":2},{"Type":"95","Earned":0,"Unearned":1,"Total":1},{"Type":"99","Earned":1,"Unearned":0,"Total":1},{"Type":"BRONZE","Earned":2206,"Unearned":1787,"Total":3993},{"Type":"GOLD","Earned":173,"Unearned":242,"Total":415},{"Type":"PLATINUM","Earned":19,"Unearned":73,"Total":92},{"Type":"SILVER","Earned":472,"Unearned":664,"Total":1136}]}}